chaosrouter_core
